{
"type": "FeatureCollection",
"name": "cambodia_select",
"crs": { "type": "name", "properties": { "name": "urn:ogc:def:crs:OGC:1.3:CRS84" } },
"features": [
{ "type": "Feature", "properties": { "fid": 7, "ID": "C7-1", "location": "Salakansaeng PS", "Lat": 13.36726666, "Lon": 103.8548639, "CDC N1": 5475.5, "PMMoV": 24453285.1, "CDCLOG": 3.7384237832977552, "PMMoVLOG": 7.3883372113109838, "clog": 4, "pmlog": 7 }, "geometry": { "type": "Point", "coordinates": [ 103.8548639, 13.36726666 ] } },
{ "type": "Feature", "properties": { "fid": 13, "ID": "C13-1", "location": "Trorlok Bek canal", "Lat": 11.57082777, "Lon": 104.8883639, "CDC N1": 3747.5, "PMMoV": 11542238.8, "CDCLOG": 3.5737416415203169, "PMMoVLOG": 7.0622900552827668, "clog": 4, "pmlog": 7 }, "geometry": { "type": "Point", "coordinates": [ 104.8883639, 11.57082777 ] } }
]
}
